webshell_generator/__init__.py
webshell_generator/utils.py
webshell_generator/webshell.py
webshell_generator/webshells/behinder4/default_aes/shell.aspx
webshell_generator/webshells/behinder4/default_aes/shell.jsp
webshell_generator/webshells/behinder4/default_aes/shell.php
webshell_generator/webshells/godzilla/cshap_aes_base64.ashx
webshell_generator/webshells/godzilla/cshap_aes_base64.aspx
webshell_generator/webshells/godzilla/java_aes_base64.jsp
webshell_generator/webshells/godzilla/java_aes_base64.jspx
webshell_generator/webshells/godzilla/php_xor_base64.php
webshell_generator/webshells/other/define_class_memshell.jsp
webshell_generator-0.1.3.dist-info/METADATA
webshell_generator-0.1.3.dist-info/WHEEL
webshell_generator-0.1.3.dist-info/top_level.txt
webshell_generator-0.1.3.dist-info/RECORD
