Metadata-Version: 2.1
Name: webshell-generator
Version: 0.1.3
Summary: A library to generate processed webshell instances
Author: haruka
Author-email: admin@haruka.com
Requires-Dist: requests
